tapkit/__init__.py
tapkit/client.py
tapkit/exceptions.py
tapkit/models.py
tapkit/phone.py
tapkit/py.typed
tapkit/geometry/__init__.py
tapkit/geometry/bbox.py
tapkit/geometry/point.py
tapkit/geometry/screen.py
tapkit/oagi/__init__.py
tapkit/oagi/async_action_handler.py
tapkit/oagi/image_provider.py
tapkit/oagi/sync_action_handler.py
tapkit-0.1.2.dist-info/METADATA
tapkit-0.1.2.dist-info/WHEEL
tapkit-0.1.2.dist-info/RECORD
