Metadata-Version: 2.4
Name: tapkit
Version: 0.1.2
Summary: Python SDK for controlling iPhones via TapKit
Requires-Python: >=3.11
Requires-Dist: httpx>=0.27.0
Requires-Dist: oagi
Requires-Dist: pillow>=10.0.0
